pdf_gen/__init__.py
pdf_gen/pdf_gen.py
tests/__init__.py
tests/test_pdf.py
pdf_gen-0.0.7.dist-info/LICENSE
pdf_gen-0.0.7.dist-info/METADATA
pdf_gen-0.0.7.dist-info/WHEEL
pdf_gen-0.0.7.dist-info/top_level.txt
pdf_gen-0.0.7.dist-info/RECORD
