Metadata-Version: 2.1
Name: pdf-gen
Version: 0.0.7
Summary: Pdf-file generator
Home-page: https://github.com/vanya2535/pdf_gen
Author: Desyatnikov I.S.
Author-email: ncab_03@mail.ru
License: UNKNOWN
Platform: any
Requires-Python: >=3.7
Requires-Dist: reportlab (>=3.5.65)
Requires-Dist: PyPDF2 (>=1.26.0)
